pynnmf/__init__.py
pynnmf/pynnmf.py
pynnmf-0.1.4.dist-info/licenses/LICENSE
pynnmf-0.1.4.dist-info/METADATA
pynnmf-0.1.4.dist-info/WHEEL
pynnmf-0.1.4.dist-info/top_level.txt
pynnmf-0.1.4.dist-info/RECORD
