Metadata-Version: 2.4
Name: pyNNMF
Version: 0.1.4
Summary: Library for computing Non-Negative Matrix Factorisation with missing values imputation.
Home-page: https://github.com/mariolpantunes/pyNNMF
Author: Mário Antunes
Author-email: mario.antunes@ua.pt
Classifier: Programming Language :: Python :: 3
Classifier: License :: OSI Approved :: MIT License
Classifier: Operating System :: OS Independent
Requires-Python: >=3.8
License-File: LICENSE
Requires-Dist: numpy>=1.23
Dynamic: license-file
